README.rst
setup.py
account_helper/__init__.py
account_helper/middleware.py
account_helper/mixins.py
account_helper/utils.py
django_account_helper.egg-info/PKG-INFO
django_account_helper.egg-info/SOURCES.txt
django_account_helper.egg-info/dependency_links.txt
django_account_helper.egg-info/top_level.txt