Metadata-Version: 1.1
Name: django-account-helper
Version: 0.1.5
Summary: django account helper utils for `django.contrib.auth`
Home-page: https://github.com/9nix00/django-account-helper
Author: wangwenpei
Author-email: wangwenpei@nextoa.com
License: http://opensource.org/licenses/MIT
Download-URL: https://github.com/9nix00/django-account-helper/archive/master.zip
Keywords: django_account_helper,
Platform: UNKNOWN
